DiscordLevelingCard/__init__.py
DiscordLevelingCard/assets/curveborder.png
DiscordLevelingCard/assets/curvedoverlay.png
DiscordLevelingCard/assets/levelfont.otf
DiscordLevelingCard/assets/mask_circle.jpg
DiscordLevelingCard/assets/mask_hexagon.png
DiscordLevelingCard/assets/overlay1.png
DiscordLevelingCard/card_settings.py
DiscordLevelingCard/discord_card.py
DiscordLevelingCard/error.py
DiscordLevelingCard/sandbox.py
DiscordLevelingCard/tester.py
discordlevelingcard-0.6.0.dist-info/LICENSE
discordlevelingcard-0.6.0.dist-info/WHEEL
discordlevelingcard-0.6.0.dist-info/METADATA
discordlevelingcard-0.6.0.dist-info/RECORD
