Metadata-Version: 2.1
Name: discordlevelingcard
Version: 0.6.0
Summary: A library with leveling cards for your discord bot.
Home-page: https://github.com/krishsharma0413/DiscordLevelingCard
License: MIT
Keywords: discord,leveling,card,image,discord.py,disnake,nextcord,rank,ranking,level,discord-bot,bot,discord-leveling,level-card,discord-leveling-card,discord-rank-card,sandbox,custom,custom-card
Author: Reset
Author-email: krishsharma0413@gmail.com
Requires-Python: >=3.8,<4
Classifier: License :: OSI Approved :: MIT License
Classifier: Programming Language :: Python :: 3
Classifier: Programming Language :: Python :: 3.10
Classifier: Programming Language :: Python :: 3.8
Classifier: Programming Language :: Python :: 3.9
Requires-Dist: Pillow (>=9.2.0,<10.0.0)
Requires-Dist: aiohttp (>=3.8.1,<4.0.0)
Requires-Dist: requests (>=2.28.1,<3.0.0)
Project-URL: Repository, https://github.com/krishsharma0413/DiscordLevelingCard
